LICENSE
README.md
setup.cfg
setup.py
Commandopt.egg-info/PKG-INFO
Commandopt.egg-info/SOURCES.txt
Commandopt.egg-info/dependency_links.txt
Commandopt.egg-info/top_level.txt
commandopt/__init__.py
commandopt/exceptions.py
commandopt/py.typed
tests/test_commandopt.py