Metadata-Version: 2.1
Name: Commandopt
Version: 0.2.1
Summary: Turn a dict of arguments into cli commands, ideal companion of docopt.
Home-page: https://github.com/jaegerbobomb/commandopt
Download-URL: https://github.com/jaegerbobomb/commandopt/archive/v0.2.1.tar.gz
Author: notmarrco
Author-email: marc@maj44.com
Classifier: Programming Language :: Python :: 3
Classifier: License :: OSI Approved :: MIT License
Classifier: Operating System :: OS Independent
Requires-Python: >=3.2
License-File: LICENSE
